jupy5/__init__.py
jupy5/sketch.py
jupy5/turtle.py
jupy5-0.0.9.dist-info/LICENSE
jupy5-0.0.9.dist-info/METADATA
jupy5-0.0.9.dist-info/WHEEL
jupy5-0.0.9.dist-info/top_level.txt
jupy5-0.0.9.dist-info/RECORD
