Metadata-Version: 2.1
Name: jupy5
Version: 0.0.9
Summary: A library for creative coding in Python using Jupyter
Home-page: https://github.com/nickmcintyre/jupy5
Author: Nick McIntyre
Author-email: nick@mcintyre.io
Project-URL: Bug Tracker, https://github.com/nickmcintyre/jupy5/issues
Classifier: Programming Language :: Python :: 3
Classifier: License :: OSI Approved :: GNU Lesser General Public License v2 or later (LGPLv2+)
Classifier: Operating System :: OS Independent
Requires-Python: >=3.10
License-File: LICENSE
Requires-Dist: ipyevents (>=2.0.1)
Requires-Dist: ipycanvas (>=0.13.1)
